.coveragerc
CITATION
CONTRIBUTING.md
COPYRIGHT
LICENSE
MANIFEST.in
README.md
RELEASE_NOTES
pyproject.toml
pytest.ini
setup.cfg
setup.py
test_requirements.txt
versioneer.py
docs/Makefile
docs/bugs.rst
docs/ciao.rst
docs/conf.py
docs/conftest.py
docs/environment.yml
docs/index.rst
docs/indices.rst
docs/install.rst
docs/quick.rst
docs/_examples/readme.txt
docs/_examples/data/index.py
docs/_examples/data/pha.py
docs/_examples/developer/ui_plot.py
docs/_examples/evaluation/convolution/psf1d.py
docs/_examples/evaluation/convolution/psf2d.py
docs/_examples/evaluation/convolution/test.py
docs/_examples/evaluation/convolution/test.ui.py
docs/_examples/evaluation/examples/pharesponses.py
docs/_examples/examples/fit_peaked_data/example.py
docs/_examples/examples/fit_peaked_data/test_peak.dat
docs/_examples/examples/simple_interpolation/example.py
docs/_examples/examples/simple_user_model/example.py
docs/_examples/examples/simple_user_model/pone.0171996.s001.xlsx
docs/_examples/extra/optimize_function.py
docs/_examples/fit/fitpath.txt
docs/_examples/fit/index.py
docs/_examples/models/combine.py
docs/_examples/plots/index.py
docs/_examples/ui/basic_session.py
docs/_examples/ui/basic_ui.py
docs/_static/copybutton.js
docs/_static/sherpa_logo.png
docs/_static/data/data1d.png
docs/_static/data/data1dint.png
docs/_static/data/data_eval_model.png
docs/_static/data/data_int_line_to_plot.png
docs/_static/data/data_int_to_plot.png
docs/_static/data/data_to_plot.png
docs/_static/data/pha_filtered.png
docs/_static/data/pha_filtered_channel.png
docs/_static/data/pha_grouping_comparison.png
docs/_static/data/pha_initial.png
docs/_static/developer/ui_plot_fit_basic.png
docs/_static/developer/ui_plot_fit_manual.png
docs/_static/evaluation/fake_pha.png
docs/_static/evaluation/pha_data.png
docs/_static/evaluation/pha_data_compare.png
docs/_static/evaluation/pha_data_manual.png
docs/_static/evaluation/pha_data_wave.png
docs/_static/evaluation/pha_eval_model_to_fit.png
sherpa.egg-info/PKG-INFO
sherpa.egg-info/SOURCES.txt
sherpa.egg-info/dependency_links.txt
sherpa.egg-info/entry_points.txt
sherpa.egg-info/requires.txt
sherpa.egg-info/top_level.txt
