Metadata-Version: 2.4
Name: sherpa
Version: 4.17.1
Summary: Modeling and fitting package for scientific data analysis
Author-email: Smithsonian Astrophysical Observatory / Chandra X-Ray Center <cxchelp@cfa.harvard.edu>
License: GNU GENERAL PUBLIC LICENSE
Project-URL: Homepage, https://cxc.harvard.edu/sherpa/
Project-URL: Documentation, https://sherpa.readthedocs.io/
Project-URL: Repository, https://github.com/sherpa/sherpa
Project-URL: Issues, https://github.com/sherpa/sherpa/issues
Classifier: Intended Audience :: Science/Research
Classifier: License :: OSI Approved :: GNU General Public License v3 or later (GPLv3+)
Classifier: Programming Language :: C
Classifier: Programming Language :: Python :: 3.10
Classifier: Programming Language :: Python :: 3.11
Classifier: Programming Language :: Python :: 3.12
Classifier: Programming Language :: Python :: 3.13
Classifier: Programming Language :: Python :: Implementation :: CPython
Classifier: Topic :: Scientific/Engineering :: Astronomy
Classifier: Topic :: Scientific/Engineering :: Physics
Requires-Python: >=3.10
License-File: LICENSE
Requires-Dist: numpy
Provides-Extra: test
Requires-Dist: pytest>=8.0; extra == "test"
Provides-Extra: doc
Requires-Dist: sphinx<8,>=5; extra == "doc"
Requires-Dist: sphinx_rtd_theme>=3.0.0; extra == "doc"
Requires-Dist: sphinx-astropy; extra == "doc"
Requires-Dist: nbsphinx; extra == "doc"
Requires-Dist: ipykernel; extra == "doc"
Requires-Dist: astropy; extra == "doc"
Requires-Dist: matplotlib; extra == "doc"
Requires-Dist: bokeh; extra == "doc"
Requires-Dist: arviz; extra == "doc"
Dynamic: license-file
